README.md
pytest_cassandra.py
setup.py
pytest_cassandra.egg-info/PKG-INFO
pytest_cassandra.egg-info/SOURCES.txt
pytest_cassandra.egg-info/dependency_links.txt
pytest_cassandra.egg-info/entry_points.txt
pytest_cassandra.egg-info/requires.txt
pytest_cassandra.egg-info/top_level.txt