Metadata-Version: 1.1
Name: pytest-cassandra
Version: 0.1.0
Summary: Cassandra CCM Test Fixtures for pytest
Home-page: https://github.com/dwoz/pytest-cassandra
Author: Daniel Wozniak
Author-email: dan@woz.io
License: UNKNOWN
Download-URL: https://github.com/dwoz/pytest-cassandra/archive/0.1.0.tar.gz
Keywords: testing,pytest,plugin,fixture,cassandra
Platform: UNKNOWN
Classifier: Development Status :: 1 - Planning
Classifier: Intended Audience :: Developers
Classifier: License :: OSI Approved :: MIT License
Classifier: Programming Language :: Python
Classifier: Topic :: Software Development :: Testing
Classifier: Topic :: Utilities
Classifier: Framework :: Pytest
